mem_sis.v
`timescale 1ns/1ns
module mem_sis(
        input wire [7:0] rem_d, mux1,
        input wire r_z, write, read, clr, mux_sel1, rem_e, rdm_e,
        input wire clk,
        output wire [7:0] rdm_out,
        output wire [7:0] test_ram0, test_ram1, test_ram2, test_ram3, test_ram4, test_ram5, test_ram6, test_ram7
    );

    //Conexoes entre blocos 
    wire [7:0] w_mem_data;

    //Registradores de Estado da Maquina
    reg [1:0] current_state, next_state;

    //Registradores de Endereço e de Dados da Memoria
    reg [7:0] rem, rdm, mux_output;

    //Memoria Ram - Vetor
    reg [7:0] mem [0:255];

    //Constantes para os estados 
    parameter wait_m = 2'b00,
        write_m = 2'b01,
        read_m = 2'b10,
        clear_m = 2'b11;

    //Logica Resgistrador de Estados
    always @ ( posedge clk or posedge r_z) begin
        if(r_z) begin
            current_state <= wait_m;
        end else begin
            current_state <= next_state;
        end
    end

    //Logica dos Registradores de dados, enderecos e memoria
    always @ ( posedge clk  or posedge r_z) begin
        if (r_z) begin
            rdm <= 8'h00;
            rem <= 8'h00;
        end else begin
            if (rdm_e) begin 
                rdm <= mux_output;
            end
            if (rem_e) begin
                rem <= rem_d;
            end
            case(current_state)
                wait_m: begin
                    //Nao faz nada
                end
                // read_m: begin     
                //     
                // end
                write_m: begin
                    mem[rem] <= rdm;
                end
                clear_m: begin
                    //mem = 0; - Ou nao limpar ou reset de todas as posicoes usando loop
                end

            endcase
        end
    end

    // Logica dos Proximos Estados
    always @ (*)begin
        next_state = current_state;
        case(current_state)
            wait_m:  begin
                if (write) begin
                    next_state = write_m;
                end else if (read) begin
                    next_state = read_m;
                end else if (clr) begin
                    next_state = clear_m;
                end
            end
            write_m:
                next_state = wait_m;
            read_m:
                next_state = wait_m;
            clear_m:
                next_state = wait_m;
            default: 
                next_state = wait_m;
        endcase
    end

    //Logica Combinacional - Independente do Clock
    always @ (*) begin
        case(mux_sel1)
            1'b0: mux_output = w_mem_data;
            1'b1: mux_output = mux1;
            default: mux_output = 8'h00;
        endcase
    end

    assign w_mem_data = current_state  == read_m ? mem[rem] : 8'h00;

    assign rdm_out = rdm;

    assign test_ram0 = mem[0];
    assign test_ram1 = mem[1];
    assign test_ram2 = mem[2];
    assign test_ram3 = mem[3];
    assign test_ram4 = mem[4];
    assign test_ram5 = mem[5];
    assign test_ram6 = mem[6];
    assign test_ram7 = mem[7];

endmodule

testbenches/mem_sis_tb.v
`timescale 1ns/1ns

module mem_sis_tb;

    reg [7:0] rem_d, mux1;
    reg r_z, write, read, clr, mux_sel1, rem_e, rdm_e;
    reg clk = 1'b0;
    wire [7:0] rdm_out;
    wire [7:0] test_ram0;
    wire [7:0] test_ram1; 
    wire [7:0] test_ram2; 
    wire [7:0] test_ram3; 
    wire [7:0] test_ram4; 
    wire [7:0] test_ram5; 
    wire [7:0] test_ram6; 
    wire [7:0] test_ram7; 

    mem_sis DUT01(
       rem_d, mux1, r_z, write, read, clr, mux_sel1, rem_e, rdm_e, clk,
       rdm_out, test_ram0, test_ram1, test_ram2, test_ram3, test_ram4, test_ram5, test_ram6, test_ram7
    );

    always #5 clk = ~clk;

    initial begin
        $dumpfile("mem_sis.vcd");
        $dumpvars(0, mem_sis_tb);
        $display("Time (ns)   | rem_d    | mux1     | r_z | write | read | clr | mux_sel1 | rem_e | rdm_e | clk");
        $monitor("%9t   | %8b | %8b | %3b | %5b | %4b | %3b | %8b | %5b | %5b | %3b", 
         $time, rem_d, mux1, r_z, write, read, clr, mux_sel1, rem_e, rdm_e, clk);

        rem_d = 8'b00000000;
        mux1 = 8'b00000000;
        r_z = 1'b0;
        write = 1'b0;
        read = 1'b0;
        clr = 1'b0;
        mux_sel1 = 1'b0;
        rem_e = 1'b0;
        rdm_e = 1'b0;
        #10; //10
        r_z = 1'b1;
        #10; //20
        r_z = 1'b0;
        mux1 = 8'b00000001;
        mux_sel1 = 1'b1;
        rdm_e = 1'b1;
        #10; //30
        rdm_e = 1'b0;
        write = 1'b1;
        #10; //40
        write = 1'b0;
        #10;
        r_z = 1'b1;
        #10; //60
        r_z = 1'b0;
        #10;
        rem_d = 8'b00000000;
        #10;
        rem_e = 1'b1;
        mux_sel1 = 1'b0;
        #10;
        rem_e = 1'b0;
        read = 1'b1;
        rdm_e = 1'b1;
        #10;
        read = 1'b0;
        #10;
        
        $finish;
    end



endmodule

mem_sis.vcd
$date
	Fri Sep  4 13:09:27 2026
$end
$version
	Icarus Verilog
$end
$timescale
	1ns
$end
$scope module mem_sis_tb $end
$var wire 8 ! test_ram7 [7:0] $end
$var wire 8 " test_ram6 [7:0] $end
$var wire 8 # test_ram5 [7:0] $end
$var wire 8 $ test_ram4 [7:0] $end
$var wire 8 % test_ram3 [7:0] $end
$var wire 8 & test_ram2 [7:0] $end
$var wire 8 ' test_ram1 [7:0] $end
$var wire 8 ( test_ram0 [7:0] $end
$var wire 8 ) rdm_out [7:0] $end
$var reg 1 * clk $end
$var reg 1 + clr $end
$var reg 8 , mux1 [7:0] $end
$var reg 1 - mux_sel1 $end
$var reg 1 . r_z $end
$var reg 1 / rdm_e $end
$var reg 1 0 read $end
$var reg 8 1 rem_d [7:0] $end
$var reg 1 2 rem_e $end
$var reg 1 3 write $end
$scope module DUT01 $end
$var wire 1 * clk $end
$var wire 1 + clr $end
$var wire 8 4 mux1 [7:0] $end
$var wire 1 - mux_sel1 $end
$var wire 1 . r_z $end
$var wire 1 / rdm_e $end
$var wire 8 5 rdm_out [7:0] $end
$var wire 1 0 read $end
$var wire 8 6 rem_d [7:0] $end
$var wire 1 2 rem_e $end
$var wire 8 7 test_ram0 [7:0] $end
$var wire 8 8 test_ram1 [7:0] $end
$var wire 8 9 test_ram2 [7:0] $end
$var wire 8 : test_ram3 [7:0] $end
$var wire 8 ; test_ram4 [7:0] $end
$var wire 8 < test_ram5 [7:0] $end
$var wire 8 = test_ram6 [7:0] $end
$var wire 8 > test_ram7 [7:0] $end
$var wire 1 3 write $end
$var wire 8 ? w_mem_data [7:0] $end
$var parameter 2 @ clear_m $end
$var parameter 2 A read_m $end
$var parameter 2 B wait_m $end
$var parameter 2 C write_m $end
$var reg 2 D current_state [1:0] $end
$var reg 8 E mux_output [7:0] $end
$var reg 2 F next_state [1:0] $end
$var reg 8 G rdm [7:0] $end
$var reg 8 H rem [7:0] $end
$upscope $end
$upscope $end
$enddefinitions $end
$comment Show the parameter values. $end
$dumpall
b1 C
b0 B
b10 A
b11 @
$end
#0
$dumpvars
bx H
bx G
b0 F
bx E
bx D
bx ?
bx >
bx =
bx <
bx ;
bx :
bx 9
bx 8
bx 7
b0 6
bx 5
b0 4
03
02
b0 1
00
0/
0.
0-
b0 ,
0+
0*
bx )
bx (
bx '
bx &
bx %
bx $
bx #
bx "
bx !
$end
#5
b0 E
b0 ?
b0 D
1*
#10
b0 H
b0 )
b0 5
b0 G
0*
1.
#15
1*
#20
b1 E
0*
1/
1-
b1 ,
b1 4
0.
#25
b1 )
b1 5
b1 G
1*
#30
b1 F
0*
13
0/
#35
b0 F
b1 D
1*
#40
b0 F
0*
03
#45
b1 (
b1 7
b0 D
1*
#50
b0 )
b0 5
b0 G
0*
1.
#55
1*
#60
0*
0.
#65
1*
#70
0*
#75
1*
#80
b0 E
0*
0-
12
#85
1*
#90
b10 F
0*
1/
10
02
#95
b1 E
b0 F
b1 ?
b10 D
1*
#100
b0 F
0*
00
#105
b0 E
b0 ?
b0 D
b1 )
b1 5
b1 G
1*
